PostTestResultsToPractiTest/ClonePTTestSet.py
PostTestResultsToPractiTest/Constants.py
PostTestResultsToPractiTest/CreatePTInstance.py
PostTestResultsToPractiTest/CreatePTTestSet.py
PostTestResultsToPractiTest/EnumClass.py
PostTestResultsToPractiTest/GetConfigValues.py
PostTestResultsToPractiTest/GetPTInstance.py
PostTestResultsToPractiTest/GetPTProjectId.py
PostTestResultsToPractiTest/GetPTTest.py
PostTestResultsToPractiTest/GetPTTestSetId.py
PostTestResultsToPractiTest/Orchestrator.py
PostTestResultsToPractiTest/PT_APIRequest.py
PostTestResultsToPractiTest/PostTestResults.py
posttestresultstopractitest-0.0.12.dist-info/METADATA
posttestresultstopractitest-0.0.12.dist-info/WHEEL
posttestresultstopractitest-0.0.12.dist-info/licenses/LICENSE
posttestresultstopractitest-0.0.12.dist-info/RECORD
