Metadata-Version: 2.3
Name: PostTestResultsToPractiTest
Version: 0.0.12
Summary: Create test set and post test results to PractiTest
Author-email: Tuyen Luan <tuyenluan@yahoo.com>, Truc Mai <truc.mai3072@gmail.com>
License-File: LICENSE
Classifier: License :: OSI Approved :: MIT License
Classifier: Operating System :: OS Independent
Classifier: Programming Language :: Python :: 3
Requires-Python: >=3.10
